atmos/__init__.py
atmos/client.py
atmos/exceptions.py
atmos/models.py
atmos/utils.py
atmos_pkg-0.1.1.dist-info/licenses/LICENSE
atmos_pkg-0.1.1.dist-info/METADATA
atmos_pkg-0.1.1.dist-info/WHEEL
atmos_pkg-0.1.1.dist-info/top_level.txt
atmos_pkg-0.1.1.dist-info/RECORD
