Metadata-Version: 2.4
Name: atmos-pkg
Version: 0.1.1
Summary: Python integration library for the Atmos payment system
Home-page: https://github.com/Muhammadali-Akbarov/atmos-pkg
Author: Muhammadali-Akbarov
Author-email: muhammadali17abc@gmail.com
Project-URL: Bug Tracker, https://github.com/Muhammadali-Akbarov/atmos-pkg/issues
Project-URL: Documentation, https://github.com/Muhammadali-Akbarov/atmos-pkg
Project-URL: Source Code, https://github.com/Muhammadali-Akbarov/atmos-pkg
Keywords: atmos,python,integration,atmos-python,python-atmos,atmos-integration,python-integration,atmos-python-integration,payment-integration,atmos-payment,python-payment,atmos-api,python-api,atmos-client,python-client,atmos-sdk,python-sdk,atmos-library,python-library,atmos-wrapper,python-wrapper,atmos-package,python-package,atmos-module,python-module
Classifier: Development Status :: 4 - Beta
Classifier: Intended Audience :: Developers
Classifier: License :: OSI Approved :: MIT License
Classifier: Programming Language :: Python :: 3
Classifier: Programming Language :: Python :: 3.7
Classifier: Programming Language :: Python :: 3.8
Classifier: Programming Language :: Python :: 3.9
Classifier: Programming Language :: Python :: 3.10
Classifier: Programming Language :: Python :: 3.11
Classifier: Programming Language :: Python :: 3.12
Classifier: Topic :: Software Development :: Libraries :: Python Modules
Requires-Python: >=3.7
License-File: LICENSE
Requires-Dist: requests>=2.25.0
Dynamic: license-file
